[
  {
    "competicion": "Copa Diputacionmemorial Carlos Duque",
    "marcador_local": 75,
    "marcador_visitante": 60,
    "fecha": "27/09/2025",
    "hora": "19:00",
    "pabellon": "PAB. Dr. JUAN CARLOS MATEO",
    "es_resultado": true,
    "estado": "finalizado",
    "jornada": "FINAL Jornada 1 - 27/09/2025",
    "categoria": "Tercera FEB - COPA MASC. - ÚNICO",
    "equipo": "OH!TELS ULB",
    "rival": "DAMEX CB ALGECIRAS",
    "ubicacion": "Visitante",
    "id": "27092025_damex-cb-algeciras_ohtels-ulb_tercera-feb-copa-masc-unico"
  },
  {
    "competicion": "Copa Diputacionmemorial Carlos Duque",
    "marcador_local": 91,
    "marcador_visitante": 92,
    "fecha": "20/09/2025",
    "hora": "20:00",
    "pabellon": "PAB. ANGELITA ALTA",
    "es_resultado": true,
    "estado": "finalizado",
    "jornada": "",
    "categoria": "Tercera FEB - COPA MASC. - ÚNICO",
    "equipo": "OH!TELS ULB",
    "rival": "BAUBLOCK GYMNÁSTICA",
    "ubicacion": "Visitante",
    "id": "20092025_baublock-gymnastica_ohtels-ulb_tercera-feb-copa-masc-unico"
  },
  {
    "competicion": "Copa Diputacionmemorial Carlos Duque",
    "marcador_local": 91,
    "marcador_visitante": 92,
    "fecha": "20/09/2025",
    "hora": "20:00",
    "pabellon": "PAB. ANGELITA ALTA",
    "es_resultado": true,
    "estado": "finalizado",
    "jornada": "SEMIFINAL Jornada 1 - 21/09/2025",
    "categoria": "Tercera FEB - COPA MASC. - ÚNICO",
    "equipo": "OH!TELS ULB",
    "rival": "BAUBLOCK GYMNÁSTICA",
    "ubicacion": "Visitante",
    "id": "20092025_baublock-gymnastica_ohtels-ulb_tercera-feb-copa-masc-unico"
  }
]