{
  "categoria": "Senior Femenino - +40 - GRUPO C",
  "competicion": "Iv Torneo Las Cortes Qv",
  "ultima_actualizacion": "2026-02-13T15:39:12.339172",
  "clasificacion": [
    {
      "equipo": "TORTUGAS +40",
      "partidos_jugados": 3,
      "partidos_ganados": 2,
      "partidos_perdidos": 1,
      "puntos_favor": 63,
      "puntos_contra": 45,
      "diferencia": 18,
      "puntos": 5,
      "posicion": 1
    },
    {
      "equipo": "SAN ROQUE +40",
      "partidos_jugados": 2,
      "partidos_ganados": 2,
      "partidos_perdidos": 0,
      "puntos_favor": 39,
      "puntos_contra": 35,
      "diferencia": 4,
      "puntos": 4,
      "posicion": 2
    },
    {
      "equipo": "SANTA Mª +40",
      "partidos_jugados": 3,
      "partidos_ganados": 0,
      "partidos_perdidos": 3,
      "puntos_favor": 40,
      "puntos_contra": 62,
      "diferencia": -22,
      "puntos": 3,
      "posicion": 3
    }
  ]
}